[
  {
    "token_id": 0,
    "level": 2,
    "bbox_3d_voxel": {
      "x_min": 0.0,
      "x_max": 32.0,
      "y_min": 0.0,
      "y_max": 32.0,
      "z_min": 0.0,
      "z_max": 32.0
    },
    "bbox_3d_mm": {
      "x_min": 0.0,
      "x_max": 87.5,
      "y_min": 0.0,
      "y_max": 87.5,
      "z_min": 0.0,
      "z_max": 88.5
    },
    "cached_boundary_flag": true,
    "cached_boundary_params": {
      "beta": 0.1,
      "neighbor_mode": "6-connected"
    }
  },
  {
    "token_id": 1,
    "level": 2,
    "bbox_3d_voxel": {
      "x_min": 32.0,
      "x_max": 64.0,
      "y_min": 0.0,
      "y_max": 32.0,
      "z_min": 0.0,
      "z_max": 32.0
    },
    "bbox_3d_mm": {
      "x_min": 87.5,
      "x_max": 175.0,
      "y_min": 0.0,
      "y_max": 87.5,
      "z_min": 0.0,
      "z_max": 88.5
    },
    "cached_boundary_flag": true,
    "cached_boundary_params": {
      "beta": 0.1,
      "neighbor_mode": "6-connected"
    }
  },
  {
    "token_id": 2,
    "level": 2,
    "bbox_3d_voxel": {
      "x_min": 64.0,
      "x_max": 96.0,
      "y_min": 0.0,
      "y_max": 32.0,
      "z_min": 0.0,
      "z_max": 32.0
    },
    "bbox_3d_mm": {
      "x_min": 175.0,
      "x_max": 262.5,
      "y_min": 0.0,
      "y_max": 87.5,
      "z_min": 0.0,
      "z_max": 88.5
    },
    "cached_boundary_flag": true,
    "cached_boundary_params": {
      "beta": 0.1,
      "neighbor_mode": "6-connected"
    }
  },
  {
    "token_id": 3,
    "level": 2,
    "bbox_3d_voxel": {
      "x_min": 96.0,
      "x_max": 128.0,
      "y_min": 0.0,
      "y_max": 32.0,
      "z_min": 0.0,
      "z_max": 32.0
    },
    "bbox_3d_mm": {
      "x_min": 262.5,
      "x_max": 350.0,
      "y_min": 0.0,
      "y_max": 87.5,
      "z_min": 0.0,
      "z_max": 88.5
    },
    "cached_boundary_flag": true,
    "cached_boundary_params": {
      "beta": 0.1,
      "neighbor_mode": "6-connected"
    }
  },
  {
    "token_id": 4,
    "level": 2,
    "bbox_3d_voxel": {
      "x_min": 0.0,
      "x_max": 32.0,
      "y_min": 32.0,
      "y_max": 64.0,
      "z_min": 0.0,
      "z_max": 32.0
    },
    "bbox_3d_mm": {
      "x_min": 0.0,
      "x_max": 87.5,
      "y_min": 87.5,
      "y_max": 175.0,
      "z_min": 0.0,
      "z_max": 88.5
    },
    "cached_boundary_flag": true,
    "cached_boundary_params": {
      "beta": 0.1,
      "neighbor_mode": "6-connected"
    }
  },
  {
    "token_id": 5,
    "level": 2,
    "bbox_3d_voxel": {
      "x_min": 32.0,
      "x_max": 64.0,
      "y_min": 32.0,
      "y_max": 64.0,
      "z_min": 0.0,
      "z_max": 32.0
    },
    "bbox_3d_mm": {
      "x_min": 87.5,
      "x_max": 175.0,
      "y_min": 87.5,
      "y_max": 175.0,
      "z_min": 0.0,
      "z_max": 88.5
    },
    "cached_boundary_flag": true,
    "cached_boundary_params": {
      "beta": 0.1,
      "neighbor_mode": "6-connected"
    }
  },
  {
    "token_id": 6,
    "level": 2,
    "bbox_3d_voxel": {
      "x_min": 64.0,
      "x_max": 96.0,
      "y_min": 32.0,
      "y_max": 64.0,
      "z_min": 0.0,
      "z_max": 32.0
    },
    "bbox_3d_mm": {
      "x_min": 175.0,
      "x_max": 262.5,
      "y_min": 87.5,
      "y_max": 175.0,
      "z_min": 0.0,
      "z_max": 88.5
    },
    "cached_boundary_flag": true,
    "cached_boundary_params": {
      "beta": 0.1,
      "neighbor_mode": "6-connected"
    }
  },
  {
    "token_id": 7,
    "level": 2,
    "bbox_3d_voxel": {
      "x_min": 96.0,
      "x_max": 128.0,
      "y_min": 32.0,
      "y_max": 64.0,
      "z_min": 0.0,
      "z_max": 32.0
    },
    "bbox_3d_mm": {
      "x_min": 262.5,
      "x_max": 350.0,
      "y_min": 87.5,
      "y_max": 175.0,
      "z_min": 0.0,
      "z_max": 88.5
    },
    "cached_boundary_flag": true,
    "cached_boundary_params": {
      "beta": 0.1,
      "neighbor_mode": "6-connected"
    }
  },
  {
    "token_id": 8,
    "level": 2,
    "bbox_3d_voxel": {
      "x_min": 0.0,
      "x_max": 32.0,
      "y_min": 64.0,
      "y_max": 96.0,
      "z_min": 0.0,
      "z_max": 32.0
    },
    "bbox_3d_mm": {
      "x_min": 0.0,
      "x_max": 87.5,
      "y_min": 175.0,
      "y_max": 262.5,
      "z_min": 0.0,
      "z_max": 88.5
    },
    "cached_boundary_flag": true,
    "cached_boundary_params": {
      "beta": 0.1,
      "neighbor_mode": "6-connected"
    }
  },
  {
    "token_id": 9,
    "level": 2,
    "bbox_3d_voxel": {
      "x_min": 32.0,
      "x_max": 64.0,
      "y_min": 64.0,
      "y_max": 96.0,
      "z_min": 0.0,
      "z_max": 32.0
    },
    "bbox_3d_mm": {
      "x_min": 87.5,
      "x_max": 175.0,
      "y_min": 175.0,
      "y_max": 262.5,
      "z_min": 0.0,
      "z_max": 88.5
    },
    "cached_boundary_flag": true,
    "cached_boundary_params": {
      "beta": 0.1,
      "neighbor_mode": "6-connected"
    }
  },
  {
    "token_id": 10,
    "level": 2,
    "bbox_3d_voxel": {
      "x_min": 64.0,
      "x_max": 96.0,
      "y_min": 64.0,
      "y_max": 96.0,
      "z_min": 0.0,
      "z_max": 32.0
    },
    "bbox_3d_mm": {
      "x_min": 175.0,
      "x_max": 262.5,
      "y_min": 175.0,
      "y_max": 262.5,
      "z_min": 0.0,
      "z_max": 88.5
    },
    "cached_boundary_flag": true,
    "cached_boundary_params": {
      "beta": 0.1,
      "neighbor_mode": "6-connected"
    }
  },
  {
    "token_id": 11,
    "level": 2,
    "bbox_3d_voxel": {
      "x_min": 96.0,
      "x_max": 128.0,
      "y_min": 64.0,
      "y_max": 96.0,
      "z_min": 0.0,
      "z_max": 32.0
    },
    "bbox_3d_mm": {
      "x_min": 262.5,
      "x_max": 350.0,
      "y_min": 175.0,
      "y_max": 262.5,
      "z_min": 0.0,
      "z_max": 88.5
    },
    "cached_boundary_flag": true,
    "cached_boundary_params": {
      "beta": 0.1,
      "neighbor_mode": "6-connected"
    }
  },
  {
    "token_id": 12,
    "level": 2,
    "bbox_3d_voxel": {
      "x_min": 0.0,
      "x_max": 32.0,
      "y_min": 96.0,
      "y_max": 128.0,
      "z_min": 0.0,
      "z_max": 32.0
    },
    "bbox_3d_mm": {
      "x_min": 0.0,
      "x_max": 87.5,
      "y_min": 262.5,
      "y_max": 350.0,
      "z_min": 0.0,
      "z_max": 88.5
    },
    "cached_boundary_flag": true,
    "cached_boundary_params": {
      "beta": 0.1,
      "neighbor_mode": "6-connected"
    }
  },
  {
    "token_id": 13,
    "level": 2,
    "bbox_3d_voxel": {
      "x_min": 32.0,
      "x_max": 64.0,
      "y_min": 96.0,
      "y_max": 128.0,
      "z_min": 0.0,
      "z_max": 32.0
    },
    "bbox_3d_mm": {
      "x_min": 87.5,
      "x_max": 175.0,
      "y_min": 262.5,
      "y_max": 350.0,
      "z_min": 0.0,
      "z_max": 88.5
    },
    "cached_boundary_flag": true,
    "cached_boundary_params": {
      "beta": 0.1,
      "neighbor_mode": "6-connected"
    }
  },
  {
    "token_id": 14,
    "level": 2,
    "bbox_3d_voxel": {
      "x_min": 64.0,
      "x_max": 96.0,
      "y_min": 96.0,
      "y_max": 128.0,
      "z_min": 0.0,
      "z_max": 32.0
    },
    "bbox_3d_mm": {
      "x_min": 175.0,
      "x_max": 262.5,
      "y_min": 262.5,
      "y_max": 350.0,
      "z_min": 0.0,
      "z_max": 88.5
    },
    "cached_boundary_flag": true,
    "cached_boundary_params": {
      "beta": 0.1,
      "neighbor_mode": "6-connected"
    }
  },
  {
    "token_id": 15,
    "level": 2,
    "bbox_3d_voxel": {
      "x_min": 96.0,
      "x_max": 128.0,
      "y_min": 96.0,
      "y_max": 128.0,
      "z_min": 0.0,
      "z_max": 32.0
    },
    "bbox_3d_mm": {
      "x_min": 262.5,
      "x_max": 350.0,
      "y_min": 262.5,
      "y_max": 350.0,
      "z_min": 0.0,
      "z_max": 88.5
    },
    "cached_boundary_flag": true,
    "cached_boundary_params": {
      "beta": 0.1,
      "neighbor_mode": "6-connected"
    }
  },
  {
    "token_id": 16,
    "level": 2,
    "bbox_3d_voxel": {
      "x_min": 0.0,
      "x_max": 32.0,
      "y_min": 0.0,
      "y_max": 32.0,
      "z_min": 32.0,
      "z_max": 64.0
    },
    "bbox_3d_mm": {
      "x_min": 0.0,
      "x_max": 87.5,
      "y_min": 0.0,
      "y_max": 87.5,
      "z_min": 88.5,
      "z_max": 177.0
    },
    "cached_boundary_flag": true,
    "cached_boundary_params": {
      "beta": 0.1,
      "neighbor_mode": "6-connected"
    }
  },
  {
    "token_id": 17,
    "level": 2,
    "bbox_3d_voxel": {
      "x_min": 32.0,
      "x_max": 64.0,
      "y_min": 0.0,
      "y_max": 32.0,
      "z_min": 32.0,
      "z_max": 64.0
    },
    "bbox_3d_mm": {
      "x_min": 87.5,
      "x_max": 175.0,
      "y_min": 0.0,
      "y_max": 87.5,
      "z_min": 88.5,
      "z_max": 177.0
    },
    "cached_boundary_flag": true,
    "cached_boundary_params": {
      "beta": 0.1,
      "neighbor_mode": "6-connected"
    }
  },
  {
    "token_id": 18,
    "level": 2,
    "bbox_3d_voxel": {
      "x_min": 64.0,
      "x_max": 96.0,
      "y_min": 0.0,
      "y_max": 32.0,
      "z_min": 32.0,
      "z_max": 64.0
    },
    "bbox_3d_mm": {
      "x_min": 175.0,
      "x_max": 262.5,
      "y_min": 0.0,
      "y_max": 87.5,
      "z_min": 88.5,
      "z_max": 177.0
    },
    "cached_boundary_flag": true,
    "cached_boundary_params": {
      "beta": 0.1,
      "neighbor_mode": "6-connected"
    }
  },
  {
    "token_id": 19,
    "level": 2,
    "bbox_3d_voxel": {
      "x_min": 96.0,
      "x_max": 128.0,
      "y_min": 0.0,
      "y_max": 32.0,
      "z_min": 32.0,
      "z_max": 64.0
    },
    "bbox_3d_mm": {
      "x_min": 262.5,
      "x_max": 350.0,
      "y_min": 0.0,
      "y_max": 87.5,
      "z_min": 88.5,
      "z_max": 177.0
    },
    "cached_boundary_flag": true,
    "cached_boundary_params": {
      "beta": 0.1,
      "neighbor_mode": "6-connected"
    }
  },
  {
    "token_id": 20,
    "level": 2,
    "bbox_3d_voxel": {
      "x_min": 0.0,
      "x_max": 32.0,
      "y_min": 32.0,
      "y_max": 64.0,
      "z_min": 32.0,
      "z_max": 64.0
    },
    "bbox_3d_mm": {
      "x_min": 0.0,
      "x_max": 87.5,
      "y_min": 87.5,
      "y_max": 175.0,
      "z_min": 88.5,
      "z_max": 177.0
    },
    "cached_boundary_flag": true,
    "cached_boundary_params": {
      "beta": 0.1,
      "neighbor_mode": "6-connected"
    }
  },
  {
    "token_id": 21,
    "level": 2,
    "bbox_3d_voxel": {
      "x_min": 32.0,
      "x_max": 64.0,
      "y_min": 32.0,
      "y_max": 64.0,
      "z_min": 32.0,
      "z_max": 64.0
    },
    "bbox_3d_mm": {
      "x_min": 87.5,
      "x_max": 175.0,
      "y_min": 87.5,
      "y_max": 175.0,
      "z_min": 88.5,
      "z_max": 177.0
    },
    "cached_boundary_flag": true,
    "cached_boundary_params": {
      "beta": 0.1,
      "neighbor_mode": "6-connected"
    }
  },
  {
    "token_id": 22,
    "level": 2,
    "bbox_3d_voxel": {
      "x_min": 64.0,
      "x_max": 96.0,
      "y_min": 32.0,
      "y_max": 64.0,
      "z_min": 32.0,
      "z_max": 64.0
    },
    "bbox_3d_mm": {
      "x_min": 175.0,
      "x_max": 262.5,
      "y_min": 87.5,
      "y_max": 175.0,
      "z_min": 88.5,
      "z_max": 177.0
    },
    "cached_boundary_flag": true,
    "cached_boundary_params": {
      "beta": 0.1,
      "neighbor_mode": "6-connected"
    }
  },
  {
    "token_id": 23,
    "level": 2,
    "bbox_3d_voxel": {
      "x_min": 96.0,
      "x_max": 128.0,
      "y_min": 32.0,
      "y_max": 64.0,
      "z_min": 32.0,
      "z_max": 64.0
    },
    "bbox_3d_mm": {
      "x_min": 262.5,
      "x_max": 350.0,
      "y_min": 87.5,
      "y_max": 175.0,
      "z_min": 88.5,
      "z_max": 177.0
    },
    "cached_boundary_flag": true,
    "cached_boundary_params": {
      "beta": 0.1,
      "neighbor_mode": "6-connected"
    }
  },
  {
    "token_id": 24,
    "level": 2,
    "bbox_3d_voxel": {
      "x_min": 0.0,
      "x_max": 32.0,
      "y_min": 64.0,
      "y_max": 96.0,
      "z_min": 32.0,
      "z_max": 64.0
    },
    "bbox_3d_mm": {
      "x_min": 0.0,
      "x_max": 87.5,
      "y_min": 175.0,
      "y_max": 262.5,
      "z_min": 88.5,
      "z_max": 177.0
    },
    "cached_boundary_flag": true,
    "cached_boundary_params": {
      "beta": 0.1,
      "neighbor_mode": "6-connected"
    }
  },
  {
    "token_id": 25,
    "level": 2,
    "bbox_3d_voxel": {
      "x_min": 32.0,
      "x_max": 64.0,
      "y_min": 64.0,
      "y_max": 96.0,
      "z_min": 32.0,
      "z_max": 64.0
    },
    "bbox_3d_mm": {
      "x_min": 87.5,
      "x_max": 175.0,
      "y_min": 175.0,
      "y_max": 262.5,
      "z_min": 88.5,
      "z_max": 177.0
    },
    "cached_boundary_flag": true,
    "cached_boundary_params": {
      "beta": 0.1,
      "neighbor_mode": "6-connected"
    }
  },
  {
    "token_id": 26,
    "level": 2,
    "bbox_3d_voxel": {
      "x_min": 64.0,
      "x_max": 96.0,
      "y_min": 64.0,
      "y_max": 96.0,
      "z_min": 32.0,
      "z_max": 64.0
    },
    "bbox_3d_mm": {
      "x_min": 175.0,
      "x_max": 262.5,
      "y_min": 175.0,
      "y_max": 262.5,
      "z_min": 88.5,
      "z_max": 177.0
    },
    "cached_boundary_flag": true,
    "cached_boundary_params": {
      "beta": 0.1,
      "neighbor_mode": "6-connected"
    }
  },
  {
    "token_id": 27,
    "level": 2,
    "bbox_3d_voxel": {
      "x_min": 96.0,
      "x_max": 128.0,
      "y_min": 64.0,
      "y_max": 96.0,
      "z_min": 32.0,
      "z_max": 64.0
    },
    "bbox_3d_mm": {
      "x_min": 262.5,
      "x_max": 350.0,
      "y_min": 175.0,
      "y_max": 262.5,
      "z_min": 88.5,
      "z_max": 177.0
    },
    "cached_boundary_flag": true,
    "cached_boundary_params": {
      "beta": 0.1,
      "neighbor_mode": "6-connected"
    }
  },
  {
    "token_id": 28,
    "level": 2,
    "bbox_3d_voxel": {
      "x_min": 0.0,
      "x_max": 32.0,
      "y_min": 96.0,
      "y_max": 128.0,
      "z_min": 32.0,
      "z_max": 64.0
    },
    "bbox_3d_mm": {
      "x_min": 0.0,
      "x_max": 87.5,
      "y_min": 262.5,
      "y_max": 350.0,
      "z_min": 88.5,
      "z_max": 177.0
    },
    "cached_boundary_flag": true,
    "cached_boundary_params": {
      "beta": 0.1,
      "neighbor_mode": "6-connected"
    }
  },
  {
    "token_id": 29,
    "level": 2,
    "bbox_3d_voxel": {
      "x_min": 64.0,
      "x_max": 96.0,
      "y_min": 96.0,
      "y_max": 128.0,
      "z_min": 32.0,
      "z_max": 64.0
    },
    "bbox_3d_mm": {
      "x_min": 175.0,
      "x_max": 262.5,
      "y_min": 262.5,
      "y_max": 350.0,
      "z_min": 88.5,
      "z_max": 177.0
    },
    "cached_boundary_flag": true,
    "cached_boundary_params": {
      "beta": 0.1,
      "neighbor_mode": "6-connected"
    }
  },
  {
    "token_id": 30,
    "level": 2,
    "bbox_3d_voxel": {
      "x_min": 96.0,
      "x_max": 128.0,
      "y_min": 96.0,
      "y_max": 128.0,
      "z_min": 32.0,
      "z_max": 64.0
    },
    "bbox_3d_mm": {
      "x_min": 262.5,
      "x_max": 350.0,
      "y_min": 262.5,
      "y_max": 350.0,
      "z_min": 88.5,
      "z_max": 177.0
    },
    "cached_boundary_flag": true,
    "cached_boundary_params": {
      "beta": 0.1,
      "neighbor_mode": "6-connected"
    }
  },
  {
    "token_id": 31,
    "level": 2,
    "bbox_3d_voxel": {
      "x_min": 0.0,
      "x_max": 32.0,
      "y_min": 0.0,
      "y_max": 32.0,
      "z_min": 64.0,
      "z_max": 96.0
    },
    "bbox_3d_mm": {
      "x_min": 0.0,
      "x_max": 87.5,
      "y_min": 0.0,
      "y_max": 87.5,
      "z_min": 177.0,
      "z_max": 265.5
    },
    "cached_boundary_flag": true,
    "cached_boundary_params": {
      "beta": 0.1,
      "neighbor_mode": "6-connected"
    }
  },
  {
    "token_id": 32,
    "level": 2,
    "bbox_3d_voxel": {
      "x_min": 32.0,
      "x_max": 64.0,
      "y_min": 0.0,
      "y_max": 32.0,
      "z_min": 64.0,
      "z_max": 96.0
    },
    "bbox_3d_mm": {
      "x_min": 87.5,
      "x_max": 175.0,
      "y_min": 0.0,
      "y_max": 87.5,
      "z_min": 177.0,
      "z_max": 265.5
    },
    "cached_boundary_flag": true,
    "cached_boundary_params": {
      "beta": 0.1,
      "neighbor_mode": "6-connected"
    }
  },
  {
    "token_id": 33,
    "level": 2,
    "bbox_3d_voxel": {
      "x_min": 64.0,
      "x_max": 96.0,
      "y_min": 0.0,
      "y_max": 32.0,
      "z_min": 64.0,
      "z_max": 96.0
    },
    "bbox_3d_mm": {
      "x_min": 175.0,
      "x_max": 262.5,
      "y_min": 0.0,
      "y_max": 87.5,
      "z_min": 177.0,
      "z_max": 265.5
    },
    "cached_boundary_flag": true,
    "cached_boundary_params": {
      "beta": 0.1,
      "neighbor_mode": "6-connected"
    }
  },
  {
    "token_id": 34,
    "level": 2,
    "bbox_3d_voxel": {
      "x_min": 0.0,
      "x_max": 32.0,
      "y_min": 32.0,
      "y_max": 64.0,
      "z_min": 64.0,
      "z_max": 96.0
    },
    "bbox_3d_mm": {
      "x_min": 0.0,
      "x_max": 87.5,
      "y_min": 87.5,
      "y_max": 175.0,
      "z_min": 177.0,
      "z_max": 265.5
    },
    "cached_boundary_flag": true,
    "cached_boundary_params": {
      "beta": 0.1,
      "neighbor_mode": "6-connected"
    }
  },
  {
    "token_id": 35,
    "level": 2,
    "bbox_3d_voxel": {
      "x_min": 32.0,
      "x_max": 64.0,
      "y_min": 32.0,
      "y_max": 64.0,
      "z_min": 64.0,
      "z_max": 96.0
    },
    "bbox_3d_mm": {
      "x_min": 87.5,
      "x_max": 175.0,
      "y_min": 87.5,
      "y_max": 175.0,
      "z_min": 177.0,
      "z_max": 265.5
    },
    "cached_boundary_flag": true,
    "cached_boundary_params": {
      "beta": 0.1,
      "neighbor_mode": "6-connected"
    }
  },
  {
    "token_id": 36,
    "level": 2,
    "bbox_3d_voxel": {
      "x_min": 64.0,
      "x_max": 96.0,
      "y_min": 32.0,
      "y_max": 64.0,
      "z_min": 64.0,
      "z_max": 96.0
    },
    "bbox_3d_mm": {
      "x_min": 175.0,
      "x_max": 262.5,
      "y_min": 87.5,
      "y_max": 175.0,
      "z_min": 177.0,
      "z_max": 265.5
    },
    "cached_boundary_flag": true,
    "cached_boundary_params": {
      "beta": 0.1,
      "neighbor_mode": "6-connected"
    }
  },
  {
    "token_id": 37,
    "level": 2,
    "bbox_3d_voxel": {
      "x_min": 96.0,
      "x_max": 128.0,
      "y_min": 32.0,
      "y_max": 64.0,
      "z_min": 64.0,
      "z_max": 96.0
    },
    "bbox_3d_mm": {
      "x_min": 262.5,
      "x_max": 350.0,
      "y_min": 87.5,
      "y_max": 175.0,
      "z_min": 177.0,
      "z_max": 265.5
    },
    "cached_boundary_flag": true,
    "cached_boundary_params": {
      "beta": 0.1,
      "neighbor_mode": "6-connected"
    }
  },
  {
    "token_id": 38,
    "level": 2,
    "bbox_3d_voxel": {
      "x_min": 0.0,
      "x_max": 32.0,
      "y_min": 64.0,
      "y_max": 96.0,
      "z_min": 64.0,
      "z_max": 96.0
    },
    "bbox_3d_mm": {
      "x_min": 0.0,
      "x_max": 87.5,
      "y_min": 175.0,
      "y_max": 262.5,
      "z_min": 177.0,
      "z_max": 265.5
    },
    "cached_boundary_flag": true,
    "cached_boundary_params": {
      "beta": 0.1,
      "neighbor_mode": "6-connected"
    }
  },
  {
    "token_id": 39,
    "level": 2,
    "bbox_3d_voxel": {
      "x_min": 32.0,
      "x_max": 64.0,
      "y_min": 64.0,
      "y_max": 96.0,
      "z_min": 64.0,
      "z_max": 96.0
    },
    "bbox_3d_mm": {
      "x_min": 87.5,
      "x_max": 175.0,
      "y_min": 175.0,
      "y_max": 262.5,
      "z_min": 177.0,
      "z_max": 265.5
    },
    "cached_boundary_flag": true,
    "cached_boundary_params": {
      "beta": 0.1,
      "neighbor_mode": "6-connected"
    }
  },
  {
    "token_id": 40,
    "level": 2,
    "bbox_3d_voxel": {
      "x_min": 64.0,
      "x_max": 96.0,
      "y_min": 64.0,
      "y_max": 96.0,
      "z_min": 64.0,
      "z_max": 96.0
    },
    "bbox_3d_mm": {
      "x_min": 175.0,
      "x_max": 262.5,
      "y_min": 175.0,
      "y_max": 262.5,
      "z_min": 177.0,
      "z_max": 265.5
    },
    "cached_boundary_flag": true,
    "cached_boundary_params": {
      "beta": 0.1,
      "neighbor_mode": "6-connected"
    }
  },
  {
    "token_id": 41,
    "level": 2,
    "bbox_3d_voxel": {
      "x_min": 96.0,
      "x_max": 128.0,
      "y_min": 64.0,
      "y_max": 96.0,
      "z_min": 64.0,
      "z_max": 96.0
    },
    "bbox_3d_mm": {
      "x_min": 262.5,
      "x_max": 350.0,
      "y_min": 175.0,
      "y_max": 262.5,
      "z_min": 177.0,
      "z_max": 265.5
    },
    "cached_boundary_flag": true,
    "cached_boundary_params": {
      "beta": 0.1,
      "neighbor_mode": "6-connected"
    }
  },
  {
    "token_id": 42,
    "level": 2,
    "bbox_3d_voxel": {
      "x_min": 0.0,
      "x_max": 32.0,
      "y_min": 96.0,
      "y_max": 128.0,
      "z_min": 64.0,
      "z_max": 96.0
    },
    "bbox_3d_mm": {
      "x_min": 0.0,
      "x_max": 87.5,
      "y_min": 262.5,
      "y_max": 350.0,
      "z_min": 177.0,
      "z_max": 265.5
    },
    "cached_boundary_flag": true,
    "cached_boundary_params": {
      "beta": 0.1,
      "neighbor_mode": "6-connected"
    }
  },
  {
    "token_id": 43,
    "level": 2,
    "bbox_3d_voxel": {
      "x_min": 32.0,
      "x_max": 64.0,
      "y_min": 96.0,
      "y_max": 128.0,
      "z_min": 64.0,
      "z_max": 96.0
    },
    "bbox_3d_mm": {
      "x_min": 87.5,
      "x_max": 175.0,
      "y_min": 262.5,
      "y_max": 350.0,
      "z_min": 177.0,
      "z_max": 265.5
    },
    "cached_boundary_flag": true,
    "cached_boundary_params": {
      "beta": 0.1,
      "neighbor_mode": "6-connected"
    }
  },
  {
    "token_id": 44,
    "level": 2,
    "bbox_3d_voxel": {
      "x_min": 64.0,
      "x_max": 96.0,
      "y_min": 96.0,
      "y_max": 128.0,
      "z_min": 64.0,
      "z_max": 96.0
    },
    "bbox_3d_mm": {
      "x_min": 175.0,
      "x_max": 262.5,
      "y_min": 262.5,
      "y_max": 350.0,
      "z_min": 177.0,
      "z_max": 265.5
    },
    "cached_boundary_flag": true,
    "cached_boundary_params": {
      "beta": 0.1,
      "neighbor_mode": "6-connected"
    }
  },
  {
    "token_id": 45,
    "level": 2,
    "bbox_3d_voxel": {
      "x_min": 96.0,
      "x_max": 128.0,
      "y_min": 96.0,
      "y_max": 128.0,
      "z_min": 64.0,
      "z_max": 96.0
    },
    "bbox_3d_mm": {
      "x_min": 262.5,
      "x_max": 350.0,
      "y_min": 262.5,
      "y_max": 350.0,
      "z_min": 177.0,
      "z_max": 265.5
    },
    "cached_boundary_flag": true,
    "cached_boundary_params": {
      "beta": 0.1,
      "neighbor_mode": "6-connected"
    }
  },
  {
    "token_id": 46,
    "level": 2,
    "bbox_3d_voxel": {
      "x_min": 0.0,
      "x_max": 32.0,
      "y_min": 0.0,
      "y_max": 32.0,
      "z_min": 96.0,
      "z_max": 128.0
    },
    "bbox_3d_mm": {
      "x_min": 0.0,
      "x_max": 87.5,
      "y_min": 0.0,
      "y_max": 87.5,
      "z_min": 265.5,
      "z_max": 354.0
    },
    "cached_boundary_flag": true,
    "cached_boundary_params": {
      "beta": 0.1,
      "neighbor_mode": "6-connected"
    }
  },
  {
    "token_id": 47,
    "level": 2,
    "bbox_3d_voxel": {
      "x_min": 32.0,
      "x_max": 64.0,
      "y_min": 0.0,
      "y_max": 32.0,
      "z_min": 96.0,
      "z_max": 128.0
    },
    "bbox_3d_mm": {
      "x_min": 87.5,
      "x_max": 175.0,
      "y_min": 0.0,
      "y_max": 87.5,
      "z_min": 265.5,
      "z_max": 354.0
    },
    "cached_boundary_flag": true,
    "cached_boundary_params": {
      "beta": 0.1,
      "neighbor_mode": "6-connected"
    }
  },
  {
    "token_id": 48,
    "level": 2,
    "bbox_3d_voxel": {
      "x_min": 64.0,
      "x_max": 96.0,
      "y_min": 0.0,
      "y_max": 32.0,
      "z_min": 96.0,
      "z_max": 128.0
    },
    "bbox_3d_mm": {
      "x_min": 175.0,
      "x_max": 262.5,
      "y_min": 0.0,
      "y_max": 87.5,
      "z_min": 265.5,
      "z_max": 354.0
    },
    "cached_boundary_flag": true,
    "cached_boundary_params": {
      "beta": 0.1,
      "neighbor_mode": "6-connected"
    }
  },
  {
    "token_id": 49,
    "level": 2,
    "bbox_3d_voxel": {
      "x_min": 0.0,
      "x_max": 32.0,
      "y_min": 32.0,
      "y_max": 64.0,
      "z_min": 96.0,
      "z_max": 128.0
    },
    "bbox_3d_mm": {
      "x_min": 0.0,
      "x_max": 87.5,
      "y_min": 87.5,
      "y_max": 175.0,
      "z_min": 265.5,
      "z_max": 354.0
    },
    "cached_boundary_flag": true,
    "cached_boundary_params": {
      "beta": 0.1,
      "neighbor_mode": "6-connected"
    }
  },
  {
    "token_id": 50,
    "level": 2,
    "bbox_3d_voxel": {
      "x_min": 32.0,
      "x_max": 64.0,
      "y_min": 32.0,
      "y_max": 64.0,
      "z_min": 96.0,
      "z_max": 128.0
    },
    "bbox_3d_mm": {
      "x_min": 87.5,
      "x_max": 175.0,
      "y_min": 87.5,
      "y_max": 175.0,
      "z_min": 265.5,
      "z_max": 354.0
    },
    "cached_boundary_flag": true,
    "cached_boundary_params": {
      "beta": 0.1,
      "neighbor_mode": "6-connected"
    }
  },
  {
    "token_id": 51,
    "level": 2,
    "bbox_3d_voxel": {
      "x_min": 64.0,
      "x_max": 96.0,
      "y_min": 32.0,
      "y_max": 64.0,
      "z_min": 96.0,
      "z_max": 128.0
    },
    "bbox_3d_mm": {
      "x_min": 175.0,
      "x_max": 262.5,
      "y_min": 87.5,
      "y_max": 175.0,
      "z_min": 265.5,
      "z_max": 354.0
    },
    "cached_boundary_flag": true,
    "cached_boundary_params": {
      "beta": 0.1,
      "neighbor_mode": "6-connected"
    }
  },
  {
    "token_id": 52,
    "level": 2,
    "bbox_3d_voxel": {
      "x_min": 96.0,
      "x_max": 128.0,
      "y_min": 32.0,
      "y_max": 64.0,
      "z_min": 96.0,
      "z_max": 128.0
    },
    "bbox_3d_mm": {
      "x_min": 262.5,
      "x_max": 350.0,
      "y_min": 87.5,
      "y_max": 175.0,
      "z_min": 265.5,
      "z_max": 354.0
    },
    "cached_boundary_flag": true,
    "cached_boundary_params": {
      "beta": 0.1,
      "neighbor_mode": "6-connected"
    }
  },
  {
    "token_id": 53,
    "level": 2,
    "bbox_3d_voxel": {
      "x_min": 0.0,
      "x_max": 32.0,
      "y_min": 64.0,
      "y_max": 96.0,
      "z_min": 96.0,
      "z_max": 128.0
    },
    "bbox_3d_mm": {
      "x_min": 0.0,
      "x_max": 87.5,
      "y_min": 175.0,
      "y_max": 262.5,
      "z_min": 265.5,
      "z_max": 354.0
    },
    "cached_boundary_flag": true,
    "cached_boundary_params": {
      "beta": 0.1,
      "neighbor_mode": "6-connected"
    }
  },
  {
    "token_id": 54,
    "level": 2,
    "bbox_3d_voxel": {
      "x_min": 32.0,
      "x_max": 64.0,
      "y_min": 64.0,
      "y_max": 96.0,
      "z_min": 96.0,
      "z_max": 128.0
    },
    "bbox_3d_mm": {
      "x_min": 87.5,
      "x_max": 175.0,
      "y_min": 175.0,
      "y_max": 262.5,
      "z_min": 265.5,
      "z_max": 354.0
    },
    "cached_boundary_flag": true,
    "cached_boundary_params": {
      "beta": 0.1,
      "neighbor_mode": "6-connected"
    }
  },
  {
    "token_id": 55,
    "level": 2,
    "bbox_3d_voxel": {
      "x_min": 64.0,
      "x_max": 96.0,
      "y_min": 64.0,
      "y_max": 96.0,
      "z_min": 96.0,
      "z_max": 128.0
    },
    "bbox_3d_mm": {
      "x_min": 175.0,
      "x_max": 262.5,
      "y_min": 175.0,
      "y_max": 262.5,
      "z_min": 265.5,
      "z_max": 354.0
    },
    "cached_boundary_flag": true,
    "cached_boundary_params": {
      "beta": 0.1,
      "neighbor_mode": "6-connected"
    }
  },
  {
    "token_id": 56,
    "level": 2,
    "bbox_3d_voxel": {
      "x_min": 0.0,
      "x_max": 32.0,
      "y_min": 96.0,
      "y_max": 128.0,
      "z_min": 96.0,
      "z_max": 128.0
    },
    "bbox_3d_mm": {
      "x_min": 0.0,
      "x_max": 87.5,
      "y_min": 262.5,
      "y_max": 350.0,
      "z_min": 265.5,
      "z_max": 354.0
    },
    "cached_boundary_flag": true,
    "cached_boundary_params": {
      "beta": 0.1,
      "neighbor_mode": "6-connected"
    }
  },
  {
    "token_id": 57,
    "level": 2,
    "bbox_3d_voxel": {
      "x_min": 32.0,
      "x_max": 64.0,
      "y_min": 96.0,
      "y_max": 128.0,
      "z_min": 96.0,
      "z_max": 128.0
    },
    "bbox_3d_mm": {
      "x_min": 87.5,
      "x_max": 175.0,
      "y_min": 262.5,
      "y_max": 350.0,
      "z_min": 265.5,
      "z_max": 354.0
    },
    "cached_boundary_flag": true,
    "cached_boundary_params": {
      "beta": 0.1,
      "neighbor_mode": "6-connected"
    }
  },
  {
    "token_id": 58,
    "level": 2,
    "bbox_3d_voxel": {
      "x_min": 64.0,
      "x_max": 96.0,
      "y_min": 96.0,
      "y_max": 128.0,
      "z_min": 96.0,
      "z_max": 128.0
    },
    "bbox_3d_mm": {
      "x_min": 175.0,
      "x_max": 262.5,
      "y_min": 262.5,
      "y_max": 350.0,
      "z_min": 265.5,
      "z_max": 354.0
    },
    "cached_boundary_flag": true,
    "cached_boundary_params": {
      "beta": 0.1,
      "neighbor_mode": "6-connected"
    }
  },
  {
    "token_id": 59,
    "level": 2,
    "bbox_3d_voxel": {
      "x_min": 96.0,
      "x_max": 128.0,
      "y_min": 96.0,
      "y_max": 128.0,
      "z_min": 96.0,
      "z_max": 128.0
    },
    "bbox_3d_mm": {
      "x_min": 262.5,
      "x_max": 350.0,
      "y_min": 262.5,
      "y_max": 350.0,
      "z_min": 265.5,
      "z_max": 354.0
    },
    "cached_boundary_flag": true,
    "cached_boundary_params": {
      "beta": 0.1,
      "neighbor_mode": "6-connected"
    }
  },
  {
    "token_id": 60,
    "level": 3,
    "bbox_3d_voxel": {
      "x_min": 32.0,
      "x_max": 48.0,
      "y_min": 96.0,
      "y_max": 112.0,
      "z_min": 32.0,
      "z_max": 48.0
    },
    "bbox_3d_mm": {
      "x_min": 87.5,
      "x_max": 131.25,
      "y_min": 262.5,
      "y_max": 306.25,
      "z_min": 88.5,
      "z_max": 132.75
    },
    "cached_boundary_flag": true,
    "cached_boundary_params": {
      "beta": 0.1,
      "neighbor_mode": "6-connected"
    }
  },
  {
    "token_id": 61,
    "level": 3,
    "bbox_3d_voxel": {
      "x_min": 48.0,
      "x_max": 64.0,
      "y_min": 96.0,
      "y_max": 112.0,
      "z_min": 32.0,
      "z_max": 48.0
    },
    "bbox_3d_mm": {
      "x_min": 131.25,
      "x_max": 175.0,
      "y_min": 262.5,
      "y_max": 306.25,
      "z_min": 88.5,
      "z_max": 132.75
    },
    "cached_boundary_flag": true,
    "cached_boundary_params": {
      "beta": 0.1,
      "neighbor_mode": "6-connected"
    }
  },
  {
    "token_id": 62,
    "level": 3,
    "bbox_3d_voxel": {
      "x_min": 32.0,
      "x_max": 48.0,
      "y_min": 112.0,
      "y_max": 128.0,
      "z_min": 32.0,
      "z_max": 48.0
    },
    "bbox_3d_mm": {
      "x_min": 87.5,
      "x_max": 131.25,
      "y_min": 306.25,
      "y_max": 350.0,
      "z_min": 88.5,
      "z_max": 132.75
    },
    "cached_boundary_flag": true,
    "cached_boundary_params": {
      "beta": 0.1,
      "neighbor_mode": "6-connected"
    }
  },
  {
    "token_id": 63,
    "level": 3,
    "bbox_3d_voxel": {
      "x_min": 48.0,
      "x_max": 64.0,
      "y_min": 112.0,
      "y_max": 128.0,
      "z_min": 32.0,
      "z_max": 48.0
    },
    "bbox_3d_mm": {
      "x_min": 131.25,
      "x_max": 175.0,
      "y_min": 306.25,
      "y_max": 350.0,
      "z_min": 88.5,
      "z_max": 132.75
    },
    "cached_boundary_flag": true,
    "cached_boundary_params": {
      "beta": 0.1,
      "neighbor_mode": "6-connected"
    }
  },
  {
    "token_id": 64,
    "level": 3,
    "bbox_3d_voxel": {
      "x_min": 32.0,
      "x_max": 48.0,
      "y_min": 96.0,
      "y_max": 112.0,
      "z_min": 48.0,
      "z_max": 64.0
    },
    "bbox_3d_mm": {
      "x_min": 87.5,
      "x_max": 131.25,
      "y_min": 262.5,
      "y_max": 306.25,
      "z_min": 132.75,
      "z_max": 177.0
    },
    "cached_boundary_flag": true,
    "cached_boundary_params": {
      "beta": 0.1,
      "neighbor_mode": "6-connected"
    }
  },
  {
    "token_id": 65,
    "level": 4,
    "bbox_3d_voxel": {
      "x_min": 48.0,
      "x_max": 56.0,
      "y_min": 96.0,
      "y_max": 104.0,
      "z_min": 48.0,
      "z_max": 56.0
    },
    "bbox_3d_mm": {
      "x_min": 131.25,
      "x_max": 153.125,
      "y_min": 262.5,
      "y_max": 284.375,
      "z_min": 132.75,
      "z_max": 154.875
    },
    "cached_boundary_flag": true,
    "cached_boundary_params": {
      "beta": 0.1,
      "neighbor_mode": "6-connected"
    }
  },
  {
    "token_id": 66,
    "level": 4,
    "bbox_3d_voxel": {
      "x_min": 56.0,
      "x_max": 64.0,
      "y_min": 96.0,
      "y_max": 104.0,
      "z_min": 48.0,
      "z_max": 56.0
    },
    "bbox_3d_mm": {
      "x_min": 153.125,
      "x_max": 175.0,
      "y_min": 262.5,
      "y_max": 284.375,
      "z_min": 132.75,
      "z_max": 154.875
    },
    "cached_boundary_flag": true,
    "cached_boundary_params": {
      "beta": 0.1,
      "neighbor_mode": "6-connected"
    }
  },
  {
    "token_id": 67,
    "level": 4,
    "bbox_3d_voxel": {
      "x_min": 48.0,
      "x_max": 56.0,
      "y_min": 104.0,
      "y_max": 112.0,
      "z_min": 48.0,
      "z_max": 56.0
    },
    "bbox_3d_mm": {
      "x_min": 131.25,
      "x_max": 153.125,
      "y_min": 284.375,
      "y_max": 306.25,
      "z_min": 132.75,
      "z_max": 154.875
    },
    "cached_boundary_flag": true,
    "cached_boundary_params": {
      "beta": 0.1,
      "neighbor_mode": "6-connected"
    }
  },
  {
    "token_id": 68,
    "level": 4,
    "bbox_3d_voxel": {
      "x_min": 56.0,
      "x_max": 64.0,
      "y_min": 104.0,
      "y_max": 112.0,
      "z_min": 48.0,
      "z_max": 56.0
    },
    "bbox_3d_mm": {
      "x_min": 153.125,
      "x_max": 175.0,
      "y_min": 284.375,
      "y_max": 306.25,
      "z_min": 132.75,
      "z_max": 154.875
    },
    "cached_boundary_flag": true,
    "cached_boundary_params": {
      "beta": 0.1,
      "neighbor_mode": "6-connected"
    }
  },
  {
    "token_id": 69,
    "level": 4,
    "bbox_3d_voxel": {
      "x_min": 32.0,
      "x_max": 40.0,
      "y_min": 112.0,
      "y_max": 120.0,
      "z_min": 48.0,
      "z_max": 56.0
    },
    "bbox_3d_mm": {
      "x_min": 87.5,
      "x_max": 109.375,
      "y_min": 306.25,
      "y_max": 328.125,
      "z_min": 132.75,
      "z_max": 154.875
    },
    "cached_boundary_flag": true,
    "cached_boundary_params": {
      "beta": 0.1,
      "neighbor_mode": "6-connected"
    }
  },
  {
    "token_id": 70,
    "level": 4,
    "bbox_3d_voxel": {
      "x_min": 40.0,
      "x_max": 48.0,
      "y_min": 112.0,
      "y_max": 120.0,
      "z_min": 48.0,
      "z_max": 56.0
    },
    "bbox_3d_mm": {
      "x_min": 109.375,
      "x_max": 131.25,
      "y_min": 306.25,
      "y_max": 328.125,
      "z_min": 132.75,
      "z_max": 154.875
    },
    "cached_boundary_flag": true,
    "cached_boundary_params": {
      "beta": 0.1,
      "neighbor_mode": "6-connected"
    }
  },
  {
    "token_id": 71,
    "level": 4,
    "bbox_3d_voxel": {
      "x_min": 56.0,
      "x_max": 64.0,
      "y_min": 112.0,
      "y_max": 120.0,
      "z_min": 48.0,
      "z_max": 56.0
    },
    "bbox_3d_mm": {
      "x_min": 153.125,
      "x_max": 175.0,
      "y_min": 306.25,
      "y_max": 328.125,
      "z_min": 132.75,
      "z_max": 154.875
    },
    "cached_boundary_flag": true,
    "cached_boundary_params": {
      "beta": 0.1,
      "neighbor_mode": "6-connected"
    }
  },
  {
    "token_id": 72,
    "level": 4,
    "bbox_3d_voxel": {
      "x_min": 32.0,
      "x_max": 40.0,
      "y_min": 120.0,
      "y_max": 128.0,
      "z_min": 48.0,
      "z_max": 56.0
    },
    "bbox_3d_mm": {
      "x_min": 87.5,
      "x_max": 109.375,
      "y_min": 328.125,
      "y_max": 350.0,
      "z_min": 132.75,
      "z_max": 154.875
    },
    "cached_boundary_flag": true,
    "cached_boundary_params": {
      "beta": 0.1,
      "neighbor_mode": "6-connected"
    }
  },
  {
    "token_id": 73,
    "level": 4,
    "bbox_3d_voxel": {
      "x_min": 40.0,
      "x_max": 48.0,
      "y_min": 120.0,
      "y_max": 128.0,
      "z_min": 48.0,
      "z_max": 56.0
    },
    "bbox_3d_mm": {
      "x_min": 109.375,
      "x_max": 131.25,
      "y_min": 328.125,
      "y_max": 350.0,
      "z_min": 132.75,
      "z_max": 154.875
    },
    "cached_boundary_flag": true,
    "cached_boundary_params": {
      "beta": 0.1,
      "neighbor_mode": "6-connected"
    }
  },
  {
    "token_id": 74,
    "level": 4,
    "bbox_3d_voxel": {
      "x_min": 48.0,
      "x_max": 56.0,
      "y_min": 120.0,
      "y_max": 128.0,
      "z_min": 48.0,
      "z_max": 56.0
    },
    "bbox_3d_mm": {
      "x_min": 131.25,
      "x_max": 153.125,
      "y_min": 328.125,
      "y_max": 350.0,
      "z_min": 132.75,
      "z_max": 154.875
    },
    "cached_boundary_flag": true,
    "cached_boundary_params": {
      "beta": 0.1,
      "neighbor_mode": "6-connected"
    }
  },
  {
    "token_id": 75,
    "level": 4,
    "bbox_3d_voxel": {
      "x_min": 48.0,
      "x_max": 56.0,
      "y_min": 96.0,
      "y_max": 104.0,
      "z_min": 56.0,
      "z_max": 64.0
    },
    "bbox_3d_mm": {
      "x_min": 131.25,
      "x_max": 153.125,
      "y_min": 262.5,
      "y_max": 284.375,
      "z_min": 154.875,
      "z_max": 177.0
    },
    "cached_boundary_flag": true,
    "cached_boundary_params": {
      "beta": 0.1,
      "neighbor_mode": "6-connected"
    }
  },
  {
    "token_id": 76,
    "level": 4,
    "bbox_3d_voxel": {
      "x_min": 56.0,
      "x_max": 64.0,
      "y_min": 96.0,
      "y_max": 104.0,
      "z_min": 56.0,
      "z_max": 64.0
    },
    "bbox_3d_mm": {
      "x_min": 153.125,
      "x_max": 175.0,
      "y_min": 262.5,
      "y_max": 284.375,
      "z_min": 154.875,
      "z_max": 177.0
    },
    "cached_boundary_flag": true,
    "cached_boundary_params": {
      "beta": 0.1,
      "neighbor_mode": "6-connected"
    }
  },
  {
    "token_id": 77,
    "level": 4,
    "bbox_3d_voxel": {
      "x_min": 48.0,
      "x_max": 56.0,
      "y_min": 104.0,
      "y_max": 112.0,
      "z_min": 56.0,
      "z_max": 64.0
    },
    "bbox_3d_mm": {
      "x_min": 131.25,
      "x_max": 153.125,
      "y_min": 284.375,
      "y_max": 306.25,
      "z_min": 154.875,
      "z_max": 177.0
    },
    "cached_boundary_flag": true,
    "cached_boundary_params": {
      "beta": 0.1,
      "neighbor_mode": "6-connected"
    }
  },
  {
    "token_id": 78,
    "level": 4,
    "bbox_3d_voxel": {
      "x_min": 32.0,
      "x_max": 40.0,
      "y_min": 112.0,
      "y_max": 120.0,
      "z_min": 56.0,
      "z_max": 64.0
    },
    "bbox_3d_mm": {
      "x_min": 87.5,
      "x_max": 109.375,
      "y_min": 306.25,
      "y_max": 328.125,
      "z_min": 154.875,
      "z_max": 177.0
    },
    "cached_boundary_flag": true,
    "cached_boundary_params": {
      "beta": 0.1,
      "neighbor_mode": "6-connected"
    }
  },
  {
    "token_id": 79,
    "level": 4,
    "bbox_3d_voxel": {
      "x_min": 40.0,
      "x_max": 48.0,
      "y_min": 112.0,
      "y_max": 120.0,
      "z_min": 56.0,
      "z_max": 64.0
    },
    "bbox_3d_mm": {
      "x_min": 109.375,
      "x_max": 131.25,
      "y_min": 306.25,
      "y_max": 328.125,
      "z_min": 154.875,
      "z_max": 177.0
    },
    "cached_boundary_flag": true,
    "cached_boundary_params": {
      "beta": 0.1,
      "neighbor_mode": "6-connected"
    }
  },
  {
    "token_id": 80,
    "level": 4,
    "bbox_3d_voxel": {
      "x_min": 32.0,
      "x_max": 40.0,
      "y_min": 120.0,
      "y_max": 128.0,
      "z_min": 56.0,
      "z_max": 64.0
    },
    "bbox_3d_mm": {
      "x_min": 87.5,
      "x_max": 109.375,
      "y_min": 328.125,
      "y_max": 350.0,
      "z_min": 154.875,
      "z_max": 177.0
    },
    "cached_boundary_flag": true,
    "cached_boundary_params": {
      "beta": 0.1,
      "neighbor_mode": "6-connected"
    }
  },
  {
    "token_id": 81,
    "level": 4,
    "bbox_3d_voxel": {
      "x_min": 40.0,
      "x_max": 48.0,
      "y_min": 120.0,
      "y_max": 128.0,
      "z_min": 56.0,
      "z_max": 64.0
    },
    "bbox_3d_mm": {
      "x_min": 109.375,
      "x_max": 131.25,
      "y_min": 328.125,
      "y_max": 350.0,
      "z_min": 154.875,
      "z_max": 177.0
    },
    "cached_boundary_flag": true,
    "cached_boundary_params": {
      "beta": 0.1,
      "neighbor_mode": "6-connected"
    }
  },
  {
    "token_id": 82,
    "level": 5,
    "bbox_3d_voxel": {
      "x_min": 56.0,
      "x_max": 60.0,
      "y_min": 120.0,
      "y_max": 124.0,
      "z_min": 48.0,
      "z_max": 52.0
    },
    "bbox_3d_mm": {
      "x_min": 153.125,
      "x_max": 164.0625,
      "y_min": 328.125,
      "y_max": 339.0625,
      "z_min": 132.75,
      "z_max": 143.8125
    },
    "cached_boundary_flag": true,
    "cached_boundary_params": {
      "beta": 0.1,
      "neighbor_mode": "6-connected"
    }
  },
  {
    "token_id": 83,
    "level": 5,
    "bbox_3d_voxel": {
      "x_min": 60.0,
      "x_max": 64.0,
      "y_min": 120.0,
      "y_max": 124.0,
      "z_min": 48.0,
      "z_max": 52.0
    },
    "bbox_3d_mm": {
      "x_min": 164.0625,
      "x_max": 175.0,
      "y_min": 328.125,
      "y_max": 339.0625,
      "z_min": 132.75,
      "z_max": 143.8125
    },
    "cached_boundary_flag": true,
    "cached_boundary_params": {
      "beta": 0.1,
      "neighbor_mode": "6-connected"
    }
  },
  {
    "token_id": 84,
    "level": 5,
    "bbox_3d_voxel": {
      "x_min": 56.0,
      "x_max": 60.0,
      "y_min": 124.0,
      "y_max": 128.0,
      "z_min": 48.0,
      "z_max": 52.0
    },
    "bbox_3d_mm": {
      "x_min": 153.125,
      "x_max": 164.0625,
      "y_min": 339.0625,
      "y_max": 350.0,
      "z_min": 132.75,
      "z_max": 143.8125
    },
    "cached_boundary_flag": true,
    "cached_boundary_params": {
      "beta": 0.1,
      "neighbor_mode": "6-connected"
    }
  },
  {
    "token_id": 85,
    "level": 5,
    "bbox_3d_voxel": {
      "x_min": 60.0,
      "x_max": 64.0,
      "y_min": 124.0,
      "y_max": 128.0,
      "z_min": 48.0,
      "z_max": 52.0
    },
    "bbox_3d_mm": {
      "x_min": 164.0625,
      "x_max": 175.0,
      "y_min": 339.0625,
      "y_max": 350.0,
      "z_min": 132.75,
      "z_max": 143.8125
    },
    "cached_boundary_flag": true,
    "cached_boundary_params": {
      "beta": 0.1,
      "neighbor_mode": "6-connected"
    }
  },
  {
    "token_id": 86,
    "level": 5,
    "bbox_3d_voxel": {
      "x_min": 56.0,
      "x_max": 60.0,
      "y_min": 120.0,
      "y_max": 124.0,
      "z_min": 52.0,
      "z_max": 56.0
    },
    "bbox_3d_mm": {
      "x_min": 153.125,
      "x_max": 164.0625,
      "y_min": 328.125,
      "y_max": 339.0625,
      "z_min": 143.8125,
      "z_max": 154.875
    },
    "cached_boundary_flag": true,
    "cached_boundary_params": {
      "beta": 0.1,
      "neighbor_mode": "6-connected"
    }
  },
  {
    "token_id": 87,
    "level": 5,
    "bbox_3d_voxel": {
      "x_min": 60.0,
      "x_max": 64.0,
      "y_min": 120.0,
      "y_max": 124.0,
      "z_min": 52.0,
      "z_max": 56.0
    },
    "bbox_3d_mm": {
      "x_min": 164.0625,
      "x_max": 175.0,
      "y_min": 328.125,
      "y_max": 339.0625,
      "z_min": 143.8125,
      "z_max": 154.875
    },
    "cached_boundary_flag": true,
    "cached_boundary_params": {
      "beta": 0.1,
      "neighbor_mode": "6-connected"
    }
  },
  {
    "token_id": 88,
    "level": 5,
    "bbox_3d_voxel": {
      "x_min": 56.0,
      "x_max": 60.0,
      "y_min": 124.0,
      "y_max": 128.0,
      "z_min": 52.0,
      "z_max": 56.0
    },
    "bbox_3d_mm": {
      "x_min": 153.125,
      "x_max": 164.0625,
      "y_min": 339.0625,
      "y_max": 350.0,
      "z_min": 143.8125,
      "z_max": 154.875
    },
    "cached_boundary_flag": true,
    "cached_boundary_params": {
      "beta": 0.1,
      "neighbor_mode": "6-connected"
    }
  },
  {
    "token_id": 89,
    "level": 5,
    "bbox_3d_voxel": {
      "x_min": 60.0,
      "x_max": 64.0,
      "y_min": 124.0,
      "y_max": 128.0,
      "z_min": 52.0,
      "z_max": 56.0
    },
    "bbox_3d_mm": {
      "x_min": 164.0625,
      "x_max": 175.0,
      "y_min": 339.0625,
      "y_max": 350.0,
      "z_min": 143.8125,
      "z_max": 154.875
    },
    "cached_boundary_flag": true,
    "cached_boundary_params": {
      "beta": 0.1,
      "neighbor_mode": "6-connected"
    }
  },
  {
    "token_id": 90,
    "level": 5,
    "bbox_3d_voxel": {
      "x_min": 56.0,
      "x_max": 60.0,
      "y_min": 104.0,
      "y_max": 108.0,
      "z_min": 56.0,
      "z_max": 60.0
    },
    "bbox_3d_mm": {
      "x_min": 153.125,
      "x_max": 164.0625,
      "y_min": 284.375,
      "y_max": 295.3125,
      "z_min": 154.875,
      "z_max": 165.9375
    },
    "cached_boundary_flag": true,
    "cached_boundary_params": {
      "beta": 0.1,
      "neighbor_mode": "6-connected"
    }
  },
  {
    "token_id": 91,
    "level": 5,
    "bbox_3d_voxel": {
      "x_min": 60.0,
      "x_max": 64.0,
      "y_min": 104.0,
      "y_max": 108.0,
      "z_min": 56.0,
      "z_max": 60.0
    },
    "bbox_3d_mm": {
      "x_min": 164.0625,
      "x_max": 175.0,
      "y_min": 284.375,
      "y_max": 295.3125,
      "z_min": 154.875,
      "z_max": 165.9375
    },
    "cached_boundary_flag": true,
    "cached_boundary_params": {
      "beta": 0.1,
      "neighbor_mode": "6-connected"
    }
  },
  {
    "token_id": 92,
    "level": 5,
    "bbox_3d_voxel": {
      "x_min": 56.0,
      "x_max": 60.0,
      "y_min": 108.0,
      "y_max": 112.0,
      "z_min": 56.0,
      "z_max": 60.0
    },
    "bbox_3d_mm": {
      "x_min": 153.125,
      "x_max": 164.0625,
      "y_min": 295.3125,
      "y_max": 306.25,
      "z_min": 154.875,
      "z_max": 165.9375
    },
    "cached_boundary_flag": true,
    "cached_boundary_params": {
      "beta": 0.1,
      "neighbor_mode": "6-connected"
    }
  },
  {
    "token_id": 93,
    "level": 5,
    "bbox_3d_voxel": {
      "x_min": 60.0,
      "x_max": 64.0,
      "y_min": 108.0,
      "y_max": 112.0,
      "z_min": 56.0,
      "z_max": 60.0
    },
    "bbox_3d_mm": {
      "x_min": 164.0625,
      "x_max": 175.0,
      "y_min": 295.3125,
      "y_max": 306.25,
      "z_min": 154.875,
      "z_max": 165.9375
    },
    "cached_boundary_flag": true,
    "cached_boundary_params": {
      "beta": 0.1,
      "neighbor_mode": "6-connected"
    }
  },
  {
    "token_id": 94,
    "level": 5,
    "bbox_3d_voxel": {
      "x_min": 48.0,
      "x_max": 52.0,
      "y_min": 112.0,
      "y_max": 116.0,
      "z_min": 56.0,
      "z_max": 60.0
    },
    "bbox_3d_mm": {
      "x_min": 131.25,
      "x_max": 142.1875,
      "y_min": 306.25,
      "y_max": 317.1875,
      "z_min": 154.875,
      "z_max": 165.9375
    },
    "cached_boundary_flag": true,
    "cached_boundary_params": {
      "beta": 0.1,
      "neighbor_mode": "6-connected"
    }
  },
  {
    "token_id": 95,
    "level": 5,
    "bbox_3d_voxel": {
      "x_min": 52.0,
      "x_max": 56.0,
      "y_min": 112.0,
      "y_max": 116.0,
      "z_min": 56.0,
      "z_max": 60.0
    },
    "bbox_3d_mm": {
      "x_min": 142.1875,
      "x_max": 153.125,
      "y_min": 306.25,
      "y_max": 317.1875,
      "z_min": 154.875,
      "z_max": 165.9375
    },
    "cached_boundary_flag": true,
    "cached_boundary_params": {
      "beta": 0.1,
      "neighbor_mode": "6-connected"
    }
  },
  {
    "token_id": 96,
    "level": 5,
    "bbox_3d_voxel": {
      "x_min": 56.0,
      "x_max": 60.0,
      "y_min": 112.0,
      "y_max": 116.0,
      "z_min": 56.0,
      "z_max": 60.0
    },
    "bbox_3d_mm": {
      "x_min": 153.125,
      "x_max": 164.0625,
      "y_min": 306.25,
      "y_max": 317.1875,
      "z_min": 154.875,
      "z_max": 165.9375
    },
    "cached_boundary_flag": true,
    "cached_boundary_params": {
      "beta": 0.1,
      "neighbor_mode": "6-connected"
    }
  },
  {
    "token_id": 97,
    "level": 5,
    "bbox_3d_voxel": {
      "x_min": 60.0,
      "x_max": 64.0,
      "y_min": 112.0,
      "y_max": 116.0,
      "z_min": 56.0,
      "z_max": 60.0
    },
    "bbox_3d_mm": {
      "x_min": 164.0625,
      "x_max": 175.0,
      "y_min": 306.25,
      "y_max": 317.1875,
      "z_min": 154.875,
      "z_max": 165.9375
    },
    "cached_boundary_flag": true,
    "cached_boundary_params": {
      "beta": 0.1,
      "neighbor_mode": "6-connected"
    }
  },
  {
    "token_id": 98,
    "level": 5,
    "bbox_3d_voxel": {
      "x_min": 48.0,
      "x_max": 52.0,
      "y_min": 116.0,
      "y_max": 120.0,
      "z_min": 56.0,
      "z_max": 60.0
    },
    "bbox_3d_mm": {
      "x_min": 131.25,
      "x_max": 142.1875,
      "y_min": 317.1875,
      "y_max": 328.125,
      "z_min": 154.875,
      "z_max": 165.9375
    },
    "cached_boundary_flag": true,
    "cached_boundary_params": {
      "beta": 0.1,
      "neighbor_mode": "6-connected"
    }
  },
  {
    "token_id": 99,
    "level": 5,
    "bbox_3d_voxel": {
      "x_min": 52.0,
      "x_max": 56.0,
      "y_min": 116.0,
      "y_max": 120.0,
      "z_min": 56.0,
      "z_max": 60.0
    },
    "bbox_3d_mm": {
      "x_min": 142.1875,
      "x_max": 153.125,
      "y_min": 317.1875,
      "y_max": 328.125,
      "z_min": 154.875,
      "z_max": 165.9375
    },
    "cached_boundary_flag": true,
    "cached_boundary_params": {
      "beta": 0.1,
      "neighbor_mode": "6-connected"
    }
  },
  {
    "token_id": 100,
    "level": 5,
    "bbox_3d_voxel": {
      "x_min": 56.0,
      "x_max": 60.0,
      "y_min": 116.0,
      "y_max": 120.0,
      "z_min": 56.0,
      "z_max": 60.0
    },
    "bbox_3d_mm": {
      "x_min": 153.125,
      "x_max": 164.0625,
      "y_min": 317.1875,
      "y_max": 328.125,
      "z_min": 154.875,
      "z_max": 165.9375
    },
    "cached_boundary_flag": true,
    "cached_boundary_params": {
      "beta": 0.1,
      "neighbor_mode": "6-connected"
    }
  },
  {
    "token_id": 101,
    "level": 5,
    "bbox_3d_voxel": {
      "x_min": 60.0,
      "x_max": 64.0,
      "y_min": 116.0,
      "y_max": 120.0,
      "z_min": 56.0,
      "z_max": 60.0
    },
    "bbox_3d_mm": {
      "x_min": 164.0625,
      "x_max": 175.0,
      "y_min": 317.1875,
      "y_max": 328.125,
      "z_min": 154.875,
      "z_max": 165.9375
    },
    "cached_boundary_flag": true,
    "cached_boundary_params": {
      "beta": 0.1,
      "neighbor_mode": "6-connected"
    }
  },
  {
    "token_id": 102,
    "level": 5,
    "bbox_3d_voxel": {
      "x_min": 48.0,
      "x_max": 52.0,
      "y_min": 120.0,
      "y_max": 124.0,
      "z_min": 56.0,
      "z_max": 60.0
    },
    "bbox_3d_mm": {
      "x_min": 131.25,
      "x_max": 142.1875,
      "y_min": 328.125,
      "y_max": 339.0625,
      "z_min": 154.875,
      "z_max": 165.9375
    },
    "cached_boundary_flag": true,
    "cached_boundary_params": {
      "beta": 0.1,
      "neighbor_mode": "6-connected"
    }
  },
  {
    "token_id": 103,
    "level": 5,
    "bbox_3d_voxel": {
      "x_min": 52.0,
      "x_max": 56.0,
      "y_min": 120.0,
      "y_max": 124.0,
      "z_min": 56.0,
      "z_max": 60.0
    },
    "bbox_3d_mm": {
      "x_min": 142.1875,
      "x_max": 153.125,
      "y_min": 328.125,
      "y_max": 339.0625,
      "z_min": 154.875,
      "z_max": 165.9375
    },
    "cached_boundary_flag": true,
    "cached_boundary_params": {
      "beta": 0.1,
      "neighbor_mode": "6-connected"
    }
  },
  {
    "token_id": 104,
    "level": 5,
    "bbox_3d_voxel": {
      "x_min": 48.0,
      "x_max": 52.0,
      "y_min": 124.0,
      "y_max": 128.0,
      "z_min": 56.0,
      "z_max": 60.0
    },
    "bbox_3d_mm": {
      "x_min": 131.25,
      "x_max": 142.1875,
      "y_min": 339.0625,
      "y_max": 350.0,
      "z_min": 154.875,
      "z_max": 165.9375
    },
    "cached_boundary_flag": true,
    "cached_boundary_params": {
      "beta": 0.1,
      "neighbor_mode": "6-connected"
    }
  },
  {
    "token_id": 105,
    "level": 5,
    "bbox_3d_voxel": {
      "x_min": 52.0,
      "x_max": 56.0,
      "y_min": 124.0,
      "y_max": 128.0,
      "z_min": 56.0,
      "z_max": 60.0
    },
    "bbox_3d_mm": {
      "x_min": 142.1875,
      "x_max": 153.125,
      "y_min": 339.0625,
      "y_max": 350.0,
      "z_min": 154.875,
      "z_max": 165.9375
    },
    "cached_boundary_flag": true,
    "cached_boundary_params": {
      "beta": 0.1,
      "neighbor_mode": "6-connected"
    }
  },
  {
    "token_id": 106,
    "level": 5,
    "bbox_3d_voxel": {
      "x_min": 56.0,
      "x_max": 60.0,
      "y_min": 124.0,
      "y_max": 128.0,
      "z_min": 56.0,
      "z_max": 60.0
    },
    "bbox_3d_mm": {
      "x_min": 153.125,
      "x_max": 164.0625,
      "y_min": 339.0625,
      "y_max": 350.0,
      "z_min": 154.875,
      "z_max": 165.9375
    },
    "cached_boundary_flag": true,
    "cached_boundary_params": {
      "beta": 0.1,
      "neighbor_mode": "6-connected"
    }
  },
  {
    "token_id": 107,
    "level": 5,
    "bbox_3d_voxel": {
      "x_min": 60.0,
      "x_max": 64.0,
      "y_min": 124.0,
      "y_max": 128.0,
      "z_min": 56.0,
      "z_max": 60.0
    },
    "bbox_3d_mm": {
      "x_min": 164.0625,
      "x_max": 175.0,
      "y_min": 339.0625,
      "y_max": 350.0,
      "z_min": 154.875,
      "z_max": 165.9375
    },
    "cached_boundary_flag": true,
    "cached_boundary_params": {
      "beta": 0.1,
      "neighbor_mode": "6-connected"
    }
  },
  {
    "token_id": 108,
    "level": 5,
    "bbox_3d_voxel": {
      "x_min": 56.0,
      "x_max": 60.0,
      "y_min": 104.0,
      "y_max": 108.0,
      "z_min": 60.0,
      "z_max": 64.0
    },
    "bbox_3d_mm": {
      "x_min": 153.125,
      "x_max": 164.0625,
      "y_min": 284.375,
      "y_max": 295.3125,
      "z_min": 165.9375,
      "z_max": 177.0
    },
    "cached_boundary_flag": true,
    "cached_boundary_params": {
      "beta": 0.1,
      "neighbor_mode": "6-connected"
    }
  },
  {
    "token_id": 109,
    "level": 5,
    "bbox_3d_voxel": {
      "x_min": 60.0,
      "x_max": 64.0,
      "y_min": 104.0,
      "y_max": 108.0,
      "z_min": 60.0,
      "z_max": 64.0
    },
    "bbox_3d_mm": {
      "x_min": 164.0625,
      "x_max": 175.0,
      "y_min": 284.375,
      "y_max": 295.3125,
      "z_min": 165.9375,
      "z_max": 177.0
    },
    "cached_boundary_flag": true,
    "cached_boundary_params": {
      "beta": 0.1,
      "neighbor_mode": "6-connected"
    }
  },
  {
    "token_id": 110,
    "level": 5,
    "bbox_3d_voxel": {
      "x_min": 56.0,
      "x_max": 60.0,
      "y_min": 108.0,
      "y_max": 112.0,
      "z_min": 60.0,
      "z_max": 64.0
    },
    "bbox_3d_mm": {
      "x_min": 153.125,
      "x_max": 164.0625,
      "y_min": 295.3125,
      "y_max": 306.25,
      "z_min": 165.9375,
      "z_max": 177.0
    },
    "cached_boundary_flag": true,
    "cached_boundary_params": {
      "beta": 0.1,
      "neighbor_mode": "6-connected"
    }
  },
  {
    "token_id": 111,
    "level": 5,
    "bbox_3d_voxel": {
      "x_min": 60.0,
      "x_max": 64.0,
      "y_min": 108.0,
      "y_max": 112.0,
      "z_min": 60.0,
      "z_max": 64.0
    },
    "bbox_3d_mm": {
      "x_min": 164.0625,
      "x_max": 175.0,
      "y_min": 295.3125,
      "y_max": 306.25,
      "z_min": 165.9375,
      "z_max": 177.0
    },
    "cached_boundary_flag": true,
    "cached_boundary_params": {
      "beta": 0.1,
      "neighbor_mode": "6-connected"
    }
  },
  {
    "token_id": 112,
    "level": 5,
    "bbox_3d_voxel": {
      "x_min": 48.0,
      "x_max": 52.0,
      "y_min": 112.0,
      "y_max": 116.0,
      "z_min": 60.0,
      "z_max": 64.0
    },
    "bbox_3d_mm": {
      "x_min": 131.25,
      "x_max": 142.1875,
      "y_min": 306.25,
      "y_max": 317.1875,
      "z_min": 165.9375,
      "z_max": 177.0
    },
    "cached_boundary_flag": true,
    "cached_boundary_params": {
      "beta": 0.1,
      "neighbor_mode": "6-connected"
    }
  },
  {
    "token_id": 113,
    "level": 5,
    "bbox_3d_voxel": {
      "x_min": 52.0,
      "x_max": 56.0,
      "y_min": 112.0,
      "y_max": 116.0,
      "z_min": 60.0,
      "z_max": 64.0
    },
    "bbox_3d_mm": {
      "x_min": 142.1875,
      "x_max": 153.125,
      "y_min": 306.25,
      "y_max": 317.1875,
      "z_min": 165.9375,
      "z_max": 177.0
    },
    "cached_boundary_flag": true,
    "cached_boundary_params": {
      "beta": 0.1,
      "neighbor_mode": "6-connected"
    }
  },
  {
    "token_id": 114,
    "level": 5,
    "bbox_3d_voxel": {
      "x_min": 56.0,
      "x_max": 60.0,
      "y_min": 112.0,
      "y_max": 116.0,
      "z_min": 60.0,
      "z_max": 64.0
    },
    "bbox_3d_mm": {
      "x_min": 153.125,
      "x_max": 164.0625,
      "y_min": 306.25,
      "y_max": 317.1875,
      "z_min": 165.9375,
      "z_max": 177.0
    },
    "cached_boundary_flag": true,
    "cached_boundary_params": {
      "beta": 0.1,
      "neighbor_mode": "6-connected"
    }
  },
  {
    "token_id": 115,
    "level": 5,
    "bbox_3d_voxel": {
      "x_min": 60.0,
      "x_max": 64.0,
      "y_min": 112.0,
      "y_max": 116.0,
      "z_min": 60.0,
      "z_max": 64.0
    },
    "bbox_3d_mm": {
      "x_min": 164.0625,
      "x_max": 175.0,
      "y_min": 306.25,
      "y_max": 317.1875,
      "z_min": 165.9375,
      "z_max": 177.0
    },
    "cached_boundary_flag": true,
    "cached_boundary_params": {
      "beta": 0.1,
      "neighbor_mode": "6-connected"
    }
  },
  {
    "token_id": 116,
    "level": 5,
    "bbox_3d_voxel": {
      "x_min": 48.0,
      "x_max": 52.0,
      "y_min": 116.0,
      "y_max": 120.0,
      "z_min": 60.0,
      "z_max": 64.0
    },
    "bbox_3d_mm": {
      "x_min": 131.25,
      "x_max": 142.1875,
      "y_min": 317.1875,
      "y_max": 328.125,
      "z_min": 165.9375,
      "z_max": 177.0
    },
    "cached_boundary_flag": true,
    "cached_boundary_params": {
      "beta": 0.1,
      "neighbor_mode": "6-connected"
    }
  },
  {
    "token_id": 117,
    "level": 5,
    "bbox_3d_voxel": {
      "x_min": 52.0,
      "x_max": 56.0,
      "y_min": 116.0,
      "y_max": 120.0,
      "z_min": 60.0,
      "z_max": 64.0
    },
    "bbox_3d_mm": {
      "x_min": 142.1875,
      "x_max": 153.125,
      "y_min": 317.1875,
      "y_max": 328.125,
      "z_min": 165.9375,
      "z_max": 177.0
    },
    "cached_boundary_flag": true,
    "cached_boundary_params": {
      "beta": 0.1,
      "neighbor_mode": "6-connected"
    }
  },
  {
    "token_id": 118,
    "level": 5,
    "bbox_3d_voxel": {
      "x_min": 56.0,
      "x_max": 60.0,
      "y_min": 116.0,
      "y_max": 120.0,
      "z_min": 60.0,
      "z_max": 64.0
    },
    "bbox_3d_mm": {
      "x_min": 153.125,
      "x_max": 164.0625,
      "y_min": 317.1875,
      "y_max": 328.125,
      "z_min": 165.9375,
      "z_max": 177.0
    },
    "cached_boundary_flag": true,
    "cached_boundary_params": {
      "beta": 0.1,
      "neighbor_mode": "6-connected"
    }
  },
  {
    "token_id": 119,
    "level": 5,
    "bbox_3d_voxel": {
      "x_min": 60.0,
      "x_max": 64.0,
      "y_min": 116.0,
      "y_max": 120.0,
      "z_min": 60.0,
      "z_max": 64.0
    },
    "bbox_3d_mm": {
      "x_min": 164.0625,
      "x_max": 175.0,
      "y_min": 317.1875,
      "y_max": 328.125,
      "z_min": 165.9375,
      "z_max": 177.0
    },
    "cached_boundary_flag": true,
    "cached_boundary_params": {
      "beta": 0.1,
      "neighbor_mode": "6-connected"
    }
  },
  {
    "token_id": 120,
    "level": 5,
    "bbox_3d_voxel": {
      "x_min": 48.0,
      "x_max": 52.0,
      "y_min": 120.0,
      "y_max": 124.0,
      "z_min": 60.0,
      "z_max": 64.0
    },
    "bbox_3d_mm": {
      "x_min": 131.25,
      "x_max": 142.1875,
      "y_min": 328.125,
      "y_max": 339.0625,
      "z_min": 165.9375,
      "z_max": 177.0
    },
    "cached_boundary_flag": true,
    "cached_boundary_params": {
      "beta": 0.1,
      "neighbor_mode": "6-connected"
    }
  },
  {
    "token_id": 121,
    "level": 5,
    "bbox_3d_voxel": {
      "x_min": 52.0,
      "x_max": 56.0,
      "y_min": 120.0,
      "y_max": 124.0,
      "z_min": 60.0,
      "z_max": 64.0
    },
    "bbox_3d_mm": {
      "x_min": 142.1875,
      "x_max": 153.125,
      "y_min": 328.125,
      "y_max": 339.0625,
      "z_min": 165.9375,
      "z_max": 177.0
    },
    "cached_boundary_flag": true,
    "cached_boundary_params": {
      "beta": 0.1,
      "neighbor_mode": "6-connected"
    }
  },
  {
    "token_id": 122,
    "level": 5,
    "bbox_3d_voxel": {
      "x_min": 56.0,
      "x_max": 60.0,
      "y_min": 120.0,
      "y_max": 124.0,
      "z_min": 60.0,
      "z_max": 64.0
    },
    "bbox_3d_mm": {
      "x_min": 153.125,
      "x_max": 164.0625,
      "y_min": 328.125,
      "y_max": 339.0625,
      "z_min": 165.9375,
      "z_max": 177.0
    },
    "cached_boundary_flag": true,
    "cached_boundary_params": {
      "beta": 0.1,
      "neighbor_mode": "6-connected"
    }
  },
  {
    "token_id": 123,
    "level": 5,
    "bbox_3d_voxel": {
      "x_min": 60.0,
      "x_max": 64.0,
      "y_min": 120.0,
      "y_max": 124.0,
      "z_min": 60.0,
      "z_max": 64.0
    },
    "bbox_3d_mm": {
      "x_min": 164.0625,
      "x_max": 175.0,
      "y_min": 328.125,
      "y_max": 339.0625,
      "z_min": 165.9375,
      "z_max": 177.0
    },
    "cached_boundary_flag": true,
    "cached_boundary_params": {
      "beta": 0.1,
      "neighbor_mode": "6-connected"
    }
  },
  {
    "token_id": 124,
    "level": 5,
    "bbox_3d_voxel": {
      "x_min": 48.0,
      "x_max": 52.0,
      "y_min": 124.0,
      "y_max": 128.0,
      "z_min": 60.0,
      "z_max": 64.0
    },
    "bbox_3d_mm": {
      "x_min": 131.25,
      "x_max": 142.1875,
      "y_min": 339.0625,
      "y_max": 350.0,
      "z_min": 165.9375,
      "z_max": 177.0
    },
    "cached_boundary_flag": true,
    "cached_boundary_params": {
      "beta": 0.1,
      "neighbor_mode": "6-connected"
    }
  },
  {
    "token_id": 125,
    "level": 5,
    "bbox_3d_voxel": {
      "x_min": 52.0,
      "x_max": 56.0,
      "y_min": 124.0,
      "y_max": 128.0,
      "z_min": 60.0,
      "z_max": 64.0
    },
    "bbox_3d_mm": {
      "x_min": 142.1875,
      "x_max": 153.125,
      "y_min": 339.0625,
      "y_max": 350.0,
      "z_min": 165.9375,
      "z_max": 177.0
    },
    "cached_boundary_flag": true,
    "cached_boundary_params": {
      "beta": 0.1,
      "neighbor_mode": "6-connected"
    }
  },
  {
    "token_id": 126,
    "level": 5,
    "bbox_3d_voxel": {
      "x_min": 56.0,
      "x_max": 60.0,
      "y_min": 124.0,
      "y_max": 128.0,
      "z_min": 60.0,
      "z_max": 64.0
    },
    "bbox_3d_mm": {
      "x_min": 153.125,
      "x_max": 164.0625,
      "y_min": 339.0625,
      "y_max": 350.0,
      "z_min": 165.9375,
      "z_max": 177.0
    },
    "cached_boundary_flag": true,
    "cached_boundary_params": {
      "beta": 0.1,
      "neighbor_mode": "6-connected"
    }
  },
  {
    "token_id": 127,
    "level": 5,
    "bbox_3d_voxel": {
      "x_min": 60.0,
      "x_max": 64.0,
      "y_min": 124.0,
      "y_max": 128.0,
      "z_min": 60.0,
      "z_max": 64.0
    },
    "bbox_3d_mm": {
      "x_min": 164.0625,
      "x_max": 175.0,
      "y_min": 339.0625,
      "y_max": 350.0,
      "z_min": 165.9375,
      "z_max": 177.0
    },
    "cached_boundary_flag": true,
    "cached_boundary_params": {
      "beta": 0.1,
      "neighbor_mode": "6-connected"
    }
  }
]